crawler/__init__.py
crawler/crawler_base.py
crawler/crawler_domain.py
crawler/main.py
crawler/stats.py
crawler/crawling/__init__.py
crawler/crawling/data_processing.py
crawler/crawling/parsers.py
crawler/crawling/searches.py
crawler/crawling/site_informations.py
crawler/crawling/web_connection.py
crawler/database/__init__.py
crawler/database/database.py
crawler/database/database_manager.py
crawler/database/database_swiftea.py
crawler/index/__init__.py
crawler/index/database_ii.py
crawler/index/ftp_manager.py
crawler/index/ftp_swiftea.py
crawler/index/index.py
crawler/index/inverted_index.py
crawler/index/inverted_index_nosql.py
crawler/index/sftp_manager.py
crawler/swiftea_bot/__init__.py
crawler/swiftea_bot/data.py
crawler/swiftea_bot/file_manager.py
crawler/swiftea_bot/links.py
crawler/swiftea_bot/module.py
crawler/tests/__init__.py
crawler/tests/crawler_test.py
crawler/tests/crawling_test.py
crawler/tests/database_test.py
crawler/tests/global_test.py
crawler/tests/index_test.py
crawler/tests/run_tests.py
crawler/tests/swiftea_bot_test.py
crawler/tests/test_data.py
swiftea_crawler-1.1.3.dist-info/LICENSE
swiftea_crawler-1.1.3.dist-info/METADATA
swiftea_crawler-1.1.3.dist-info/WHEEL
swiftea_crawler-1.1.3.dist-info/top_level.txt
swiftea_crawler-1.1.3.dist-info/RECORD
