Metadata-Version: 2.1
Name: swiftea-crawler
Version: 1.1.3
Summary: Swiftea's Open Source Web Crawler
Home-page: https://github.com/Swiftea/Crawler
Author: Thykof
Author-email: thykof@protonmail.ch
License: GNU GPL v3
Keywords: crawler swiftea
Platform: UNKNOWN
Classifier: Development Status :: 5 - Production/Stable
Classifier: Topic :: Internet :: WWW/HTTP :: Indexing/Search
Classifier: License :: OSI Approved :: GNU General Public License v3 (GPLv3)
Classifier: Operating System :: OS Independent
Classifier: Programming Language :: Python :: 3
Requires-Dist: PyMySQL (==0.9.3)
Requires-Dist: coverage (==4.5.3)
Requires-Dist: dnspython (==1.16.0)
Requires-Dist: paramiko (==2.5.0)
Requires-Dist: pymodm (==0.4.1)
Requires-Dist: pymongo (==3.8.0)
Requires-Dist: pytest (==5.0.1)
Requires-Dist: reppy (==0.4.13)
Requires-Dist: requests
Requires-Dist: sphinx-rtd-theme (==0.4.3)
Provides-Extra: testing
Requires-Dist: coverage ; extra == 'testing'
Requires-Dist: pytest ; extra == 'testing'
